sqlalchemy_filtering/__init__.py
sqlalchemy_filtering/exceptions.py
sqlalchemy_filtering/filter_util.py
sqlalchemy_filtering/operators.py
sqlalchemy_filtering/sort_util.py
sqlalchemy_filtering/validators.py
sqlalchemy_filtering-0.1.2.dist-info/LICENSE
sqlalchemy_filtering-0.1.2.dist-info/METADATA
sqlalchemy_filtering-0.1.2.dist-info/WHEEL
sqlalchemy_filtering-0.1.2.dist-info/top_level.txt
sqlalchemy_filtering-0.1.2.dist-info/zip-safe
sqlalchemy_filtering-0.1.2.dist-info/RECORD
