Metadata-Version: 2.1
Name: sqlalchemy-filtering
Version: 0.1.2
Summary: SQLAlchemy query filtering and sorting wrapper in JSON format.
Home-page: https://github.com/cnatsis/sqlalchemy-filtering
Author: Christos Natsis
Author-email: christos_na@hotmail.com
License: Apache License, Version 2.0
Project-URL: Issues Tracker, https://github.com/cnatsis/sqlalchemy-filtering/issues
Platform: UNKNOWN
Classifier: Programming Language :: Python :: 3
Classifier: Programming Language :: Python :: 3.6
Classifier: Programming Language :: Python :: 3.8
Classifier: License :: OSI Approved :: Apache Software License
Classifier: Operating System :: OS Independent
Classifier: Topic :: Database
Requires-Python: >=3.6
License-File: LICENSE
Provides-Extra: mysql
Requires-Dist: mysqlclient (==2.1.0) ; extra == 'mysql'
Provides-Extra: postgresql
Requires-Dist: psycopg2 (==2.8.4) ; extra == 'postgresql'
